detoxai/__init__.py
detoxai/py.typed
detoxai/cavs/__init__.py
detoxai/cavs/cav.py
detoxai/cavs/extract_activations.py
detoxai/cavs/mass_mean_probe.py
detoxai/core/__init__.py
detoxai/core/evaluation.py
detoxai/core/interface.py
detoxai/core/interface_helpers.py
detoxai/core/mcda_helpers.py
detoxai/core/model_wrappers.py
detoxai/core/results_class.py
detoxai/core/xai.py
detoxai/datasets/README.md
detoxai/datasets/__init__.py
detoxai/datasets/catalog/__init__.py
detoxai/datasets/catalog/download.py
detoxai/datasets/catalog/torchvision_utils.py
detoxai/datasets/catalog/caltech101/handler.py
detoxai/datasets/catalog/caltech101/links.yaml
detoxai/datasets/catalog/celeba/comment.txt
detoxai/datasets/catalog/celeba/handler.py
detoxai/datasets/catalog/celeba/links.yaml
detoxai/datasets/catalog/cifar10/handler.py
detoxai/datasets/catalog/cifar10/links.yaml
detoxai/datasets/catalog/cifar100/handler.py
detoxai/datasets/catalog/cifar100/links.yaml
detoxai/datasets/catalog/fairface/analysis.ipynb
detoxai/datasets/catalog/fairface/comment.txt
detoxai/datasets/catalog/fairface/handler.py
detoxai/datasets/catalog/fairface/links.yaml
detoxai/methods/__init__.py
detoxai/methods/model_correction.py
detoxai/methods/utils.py
detoxai/methods/clarcs/__init__.py
detoxai/methods/clarcs/aclarc.py
detoxai/methods/clarcs/clarc.py
detoxai/methods/clarcs/hooks.py
detoxai/methods/clarcs/pclarc.py
detoxai/methods/clarcs/rrclarc.py
detoxai/methods/leace/__init__.py
detoxai/methods/leace/leace.py
detoxai/methods/other/__init__.py
detoxai/methods/other/fine_tune.py
detoxai/methods/posthoc/__init__.py
detoxai/methods/posthoc/naive_threshold.py
detoxai/methods/posthoc/posthoc_base.py
detoxai/methods/posthoc/reject_option_classification.py
detoxai/methods/savani/__init__.py
detoxai/methods/savani/adversarial.py
detoxai/methods/savani/lay_wis_opt.py
detoxai/methods/savani/random_perturbation.py
detoxai/methods/savani/savani_base.py
detoxai/methods/savani/utils.py
detoxai/methods/savani/zhang.py
detoxai-0.3.8.dist-info/METADATA
detoxai-0.3.8.dist-info/WHEEL
detoxai-0.3.8.dist-info/licenses/LICENSE
detoxai-0.3.8.dist-info/RECORD
