Metadata-Version: 2.4
Name: detoxai
Version: 0.3.8
Summary: todo
Author-email: Łukasz Sztukiewicz <contact@lukaszsztukiewicz.com>, Ignacy Stępka <ignacy.stepka@student.put.poznan.pl>, Michał Wiliński <michal.wilinski@student.put.poznan.pl>
License-File: LICENSE
Requires-Python: >=3.11
Requires-Dist: concept-erasure>=0.2.4
Requires-Dist: gdown>=5.2.0
Requires-Dist: lightning>=2.4.0
Requires-Dist: matplotlib>=3.10.0
Requires-Dist: pandas>=2.2.3
Requires-Dist: pillow>=11.0.0
Requires-Dist: scikit-learn>=1.6.0
Requires-Dist: scikit-optimize>=0.10.2
Requires-Dist: torchvision>=0.20.1
Requires-Dist: tqdm>=4.67.1
Requires-Dist: zennit>=0.5.1
